mozichem_hub/__init__.py
mozichem_hub/app.py
mozichem_hub/api/__init__.py
mozichem_hub/api/api_builder.py
mozichem_hub/api/main.py
mozichem_hub/config/__init__.py
mozichem_hub/config/constants.py
mozichem_hub/config/modules.py
mozichem_hub/config/settings.py
mozichem_hub/descriptors/__init__.py
mozichem_hub/descriptors/main.py
mozichem_hub/descriptors/mcp_descriptor.py
mozichem_hub/descriptors/prlcore.yml
mozichem_hub/descriptors/ptdbcore.yml
mozichem_hub/descriptors/ptfcore.yml
mozichem_hub/descriptors/ptmcore.yml
mozichem_hub/descriptors/tdcore.yml
mozichem_hub/docs/__init__.py
mozichem_hub/docs/core.py
mozichem_hub/docs/mcp.py
mozichem_hub/docs/mcp_hub.py
mozichem_hub/docs/registry.py
mozichem_hub/docs/server.py
mozichem_hub/errors/__init__.py
mozichem_hub/errors/api_exceptions.py
mozichem_hub/errors/mcp_exceptions.py
mozichem_hub/errors/ptf_exceptions.py
mozichem_hub/errors/ptm_exceptions.py
mozichem_hub/errors/reference_exceptions.py
mozichem_hub/errors/resource_exceptions.py
mozichem_hub/errors/tool_exceptions.py
mozichem_hub/errors/utils_exceptions.py
mozichem_hub/executors/__init__.py
mozichem_hub/executors/executer.py
mozichem_hub/models/__init__.py
mozichem_hub/models/mcp_models.py
mozichem_hub/models/references_models.py
mozichem_hub/models/resources_models.py
mozichem_hub/models/uni_models.py
mozichem_hub/prebuilt/__init__.py
mozichem_hub/prebuilt/manager.py
mozichem_hub/references/__init__.py
mozichem_hub/references/config.md
mozichem_hub/references/config.py
mozichem_hub/references/contents.py
mozichem_hub/references/link.py
mozichem_hub/references/reference_adapter.py
mozichem_hub/references/reference_controller.py
mozichem_hub/references/reference_mapper.py
mozichem_hub/references/reference_services.py
mozichem_hub/references/references_initializer.py
mozichem_hub/references/referencethermodb_controller.py
mozichem_hub/references/symbols.py
mozichem_hub/references/symbols.yml
mozichem_hub/resources/__init__.py
mozichem_hub/resources/class_builder.py
mozichem_hub-0.1.3.dist-info/licenses/LICENSE
mozichem_hub-0.1.3.dist-info/METADATA
mozichem_hub-0.1.3.dist-info/WHEEL
mozichem_hub-0.1.3.dist-info/top_level.txt
mozichem_hub-0.1.3.dist-info/RECORD
