Metadata-Version: 2.4
Name: mozichem-hub
Version: 0.1.3
Summary: MoziChem-Hub
Author-email: Sina Gilassi <sina.gilassi@gmail.com>
License-Expression: MIT
Project-URL: Homepage, https://github.com/sinagilassi/mozichem-hub
Classifier: Programming Language :: Python :: 3.11
Classifier: Operating System :: OS Independent
Requires-Python: >=3.11
License-File: LICENSE
Requires-Dist: fastapi>=0.116.1
Requires-Dist: fastmcp>=2.12.2
Requires-Dist: pydantic>=2.11.7
Requires-Dist: pydantic-settings>=2.10.1
Requires-Dist: pyyaml>=6.0.2
Requires-Dist: uvicorn>=0.35.0
Requires-Dist: websockets>=15.0.1
Requires-Dist: pythermodb
Requires-Dist: pythermoflash
Requires-Dist: pythermolinkdb
Requires-Dist: pythermomodels
Dynamic: license-file
